setup.py
pickone/__init__.py
pickone/pickone.py
pickone.egg-info/PKG-INFO
pickone.egg-info/SOURCES.txt
pickone.egg-info/dependency_links.txt
pickone.egg-info/top_level.txt