Metadata-Version: 1.0
Name: pickone
Version: 0.1.2
Summary: PickOne is a small handy library designed    let the user choose between a set of values
Home-page: https://github.com/riccardocagnasso/pickone
Author: Riccardo Cagnasso
Author-email: riccardo@phascode.org
License: MIT
Keywords: python input choices shell
Platform: UNKNOWN
